solaredge_influxdb/__init__.py
solaredge_influxdb/__main__.py
solaredge_influxdb/app.py
solaredge_influxdb/config.toml
solaredge_influxdb/influxdb/__init__.py
solaredge_influxdb/influxdb/client.py
solaredge_influxdb/solaredge/__init__.py
solaredge_influxdb/solaredge/client.py
solaredge_influxdb/solaredge/equipment.py
solaredge_influxdb/solaredge/meters.py
solaredge_influxdb/solaredge/models.py
solaredge_influxdb/solaredge/site.py
solaredge_influxdb-1.4.3.dist-info/LICENSE
solaredge_influxdb-1.4.3.dist-info/METADATA
solaredge_influxdb-1.4.3.dist-info/WHEEL
solaredge_influxdb-1.4.3.dist-info/RECORD
